examples/api/test_api.py
examples/performance/bench_test.py
gautomator/__init__.py
gautomator/const/__const.py
gautomator/const/__init__.py
gautomator/const/api/__init__.py
gautomator/const/api/api.py
gautomator/const/api/request.py
gautomator/const/api/swagger.py
gautomator/const/common/__init__.py
gautomator/const/common/color_const.py
gautomator/const/common/common_const.py
gautomator/const/common/emoji_const.py
gautomator/const/common/environment_const.py
gautomator/const/common/key_codes_const.py
gautomator/const/common/msg_const.py
gautomator/const/common/path_const.py
gautomator/const/common/store_const.py
gautomator/const/common/string_const.py
gautomator/const/common/times_const.py
gautomator/const/common/types_const.py
gautomator/const/config/__init__.py
gautomator/const/config/testlink_const.py
gautomator/const/custom_exception/__init__.py
gautomator/const/custom_exception/custom_exception.py
gautomator/const/database/__init__.py
gautomator/const/database/db_const.py
gautomator/const/mobile/__init__.py
gautomator/const/mobile/appium_server_const.py
gautomator/const/mobile/capabilities_const.py
gautomator/const/mobile/command_const.py
gautomator/const/mobile/device_const.py
gautomator/const/mobile/mobile_command_const.py
gautomator/const/web/__init__.py
gautomator/const/web/browsers_const.py
gautomator/decorators/__init__.py
gautomator/decorators/deprecated.py
gautomator/decorators/handle_exception.py
gautomator/decorators/parse_config.py
gautomator/decorators/retry.py
gautomator/factory/__init__.py
gautomator/factory/database_factory/__init__.py
gautomator/factory/database_factory/database_conn_generator.py
gautomator/factory/database_factory/database_factory.py
gautomator/factory/driver_factory/__init__.py
gautomator/factory/driver_factory/appium/__init__.py
gautomator/factory/driver_factory/appium/appium_actions.py
gautomator/factory/driver_factory/appium/appium_server.py
gautomator/factory/driver_factory/appium/application_helper.py
gaugetomator-0.0.2.dist-info/LICENSE
gaugetomator-0.0.2.dist-info/METADATA
gaugetomator-0.0.2.dist-info/WHEEL
gaugetomator-0.0.2.dist-info/top_level.txt
gaugetomator-0.0.2.dist-info/RECORD
